pdfcomparator-0.3.0.dist-info/top_level.txt
pdfcomparator-0.3.0.dist-info/RECORD
pdfcomparator-0.3.0.dist-info/DESCRIPTION.rst
pdfcomparator-0.3.0.dist-info/WHEEL
pdfcomparator-0.3.0.dist-info/METADATA
pdfcomparator-0.3.0.dist-info/metadata.json
pdfcomparator/pdfcompare.py
pdfcomparator/__init__.py
