Metadata-Version: 2.0
Name: pdfcomparator
Version: 0.3.0
Summary: Compares two PDF files by appearance, not by content.
Home-page: https://github.com/magmax/pdfcomparator
Author: Miguel Ángel García
Author-email: miguelangel.garcia@gmail.com
License: MIT
Keywords: pdf comparator
Platform: UNKNOWN
Classifier: Development Status :: 5 - Production/Stable
Classifier: Programming Language :: Python :: 2.7
Classifier: Programming Language :: Python :: 3.2
Classifier: Programming Language :: Python :: 3.3
Classifier: Programming Language :: Python :: 3.4
Classifier: Environment :: Console
Classifier: Intended Audience :: Developers
Classifier: License :: OSI Approved :: MIT License
Classifier: Operating System :: OS Independent
Requires-Dist: pypoppler
Requires-Dist: pycairo (==1.8.8)
